tickit_devices/__init__.py
tickit_devices/__main__.py
tickit_devices/_version.py
tickit_devices/cryostream/__init__.py
tickit_devices/cryostream/base.py
tickit_devices/cryostream/cryostream.py
tickit_devices/cryostream/states.py
tickit_devices/cryostream/status.py
tickit_devices/eiger/__init__.py
tickit_devices/eiger/eiger.py
tickit_devices/eiger/eiger_adapters.py
tickit_devices/eiger/eiger_schema.py
tickit_devices/eiger/eiger_settings.py
tickit_devices/eiger/eiger_status.py
tickit_devices/eiger/data/__init__.py
tickit_devices/eiger/data/dummy_image.py
tickit_devices/eiger/data/frame_sample
tickit_devices/eiger/data/schema.py
tickit_devices/eiger/filewriter/__init__.py
tickit_devices/eiger/filewriter/filewriter_config.py
tickit_devices/eiger/filewriter/filewriter_status.py
tickit_devices/eiger/monitor/__init__.py
tickit_devices/eiger/monitor/monitor_config.py
tickit_devices/eiger/monitor/monitor_status.py
tickit_devices/eiger/stream/__init__.py
tickit_devices/eiger/stream/eiger_stream.py
tickit_devices/eiger/stream/stream_config.py
tickit_devices/eiger/stream/stream_status.py
tickit_devices/femto/__init__.py
tickit_devices/femto/current.py
tickit_devices/femto/femto.py
tickit_devices/femto/record.db
tickit_devices/pneumatic/__init__.py
tickit_devices/pneumatic/pneumatic.py
tickit_devices/pneumatic/db_files/__init__.py
tickit_devices/pneumatic/db_files/filter1.db
tickit_devices/synchrotron/__init__.py
tickit_devices/synchrotron/synchrotron_current.py
tickit_devices/synchrotron/synchrotron_machine.py
tickit_devices/synchrotron/synchrotron_topup.py
tickit_devices/synchrotron/db_files/DCCT.db
tickit_devices/synchrotron/db_files/FILL.db
tickit_devices/synchrotron/db_files/MSTAT.db
tickit_devices/zebra/__init__.py
tickit_devices/zebra/_common.py
tickit_devices/zebra/and_or_block.py
tickit_devices/zebra/zebra.py
tickit_devices-0.3.1.dist-info/LICENSE
tickit_devices-0.3.1.dist-info/METADATA
tickit_devices-0.3.1.dist-info/WHEEL
tickit_devices-0.3.1.dist-info/entry_points.txt
tickit_devices-0.3.1.dist-info/top_level.txt
tickit_devices-0.3.1.dist-info/RECORD
