Metadata-Version: 2.1
Name: tickit-devices
Version: 0.3.1
Summary: Devices for tickit, an event-based device simulation framework
Author-email: Abigail Emery <abigail.emery@diamond.ac.uk>
License: Apache License
Project-URL: GitHub, https://github.com/dls-controls/tickit-devices
Classifier: Development Status :: 3 - Alpha
Classifier: License :: OSI Approved :: Apache Software License
Classifier: Programming Language :: Python :: 3.9
Classifier: Programming Language :: Python :: 3.10
Requires-Python: >=3.9
License-File: LICENSE
Requires-Dist: tickit >=0.4.3
Requires-Dist: typing-extensions
Requires-Dist: softioc
Requires-Dist: pydantic >1
Requires-Dist: apischema
Provides-Extra: dev
Requires-Dist: black ; extra == 'dev'
Requires-Dist: mypy ; extra == 'dev'
Requires-Dist: flake8-isort ; extra == 'dev'
Requires-Dist: Flake8-pyproject ; extra == 'dev'
Requires-Dist: pipdeptree ; extra == 'dev'
Requires-Dist: pre-commit ; extra == 'dev'
Requires-Dist: pydata-sphinx-theme >=0.12 ; extra == 'dev'
Requires-Dist: pytest-cov ; extra == 'dev'
Requires-Dist: pytest-mock ; extra == 'dev'
Requires-Dist: pytest-mypy ; extra == 'dev'
Requires-Dist: pytest-flake8 ; extra == 'dev'
Requires-Dist: pytest-black ; extra == 'dev'
Requires-Dist: pytest-asyncio ; extra == 'dev'
Requires-Dist: pytest-pydocstyle ; extra == 'dev'
Requires-Dist: sphinx-autobuild ; extra == 'dev'
Requires-Dist: sphinx-copybutton ; extra == 'dev'
Requires-Dist: sphinx-design ; extra == 'dev'
Requires-Dist: tox-direct ; extra == 'dev'
Requires-Dist: mock ; extra == 'dev'
Requires-Dist: types-mock ; extra == 'dev'
Requires-Dist: types-PyYAML ; extra == 'dev'
Requires-Dist: aioca ; extra == 'dev'
